la_stopwatch/__init__.py
la_stopwatch/abstraction.py
la_stopwatch/stopwatch.py
la_stopwatch/stopwatch_ns.py
la_stopwatch/utility.py
la_stopwatch-0.0.9.dist-info/WHEEL
la_stopwatch-0.0.9.dist-info/METADATA
la_stopwatch-0.0.9.dist-info/license_files/LICENSE
la_stopwatch-0.0.9.dist-info/RECORD
