Metadata-Version: 2.1
Name: la-stopwatch
Version: 0.0.9
Summary: Measure the amount of time that elapses between lap times
License: MIT
Keywords: stopwatch,timer,timing,clock
Author-email: thiagola92 <thiagola92@gmail.com>
Requires-Python: >=3.10
Classifier: License :: OSI Approved :: MIT License
Classifier: Operating System :: OS Independent
Classifier: Programming Language :: Python :: 3.10
Project-URL: Homepage, https://github.com/thiagola92/la-stopwatch
